demobymaruf/__about__.py
demobymaruf/__init__.py
demobymaruf/add_numbers.py
demobymaruf-0.0.1.dist-info/METADATA
demobymaruf-0.0.1.dist-info/WHEEL
demobymaruf-0.0.1.dist-info/licenses/LICENSE.txt
demobymaruf-0.0.1.dist-info/RECORD
