Metadata-Version: 2.4
Name: demobymaruf
Version: 0.0.1
Project-URL: Documentation, https://github.com/Maaruuuf/demobymaruf#readme
Project-URL: Issues, https://github.com/Maaruuuf/demobymaruf/issues
Project-URL: Source, https://github.com/Maaruuuf/demobymaruf
Author-email: Maaruuuf <abc.maruf12@gmail.com>
License-Expression: MIT
License-File: LICENSE.txt
Classifier: Development Status :: 4 - Beta
Classifier: Programming Language :: Python
Classifier: Programming Language :: Python :: 3.8
Classifier: Programming Language :: Python :: 3.9
Classifier: Programming Language :: Python :: 3.10
Classifier: Programming Language :: Python :: 3.11
Classifier: Programming Language :: Python :: 3.12
Classifier: Programming Language :: Python :: Implementation :: CPython
Classifier: Programming Language :: Python :: Implementation :: PyPy
Requires-Python: >=3.8
